{
  "response": {
    "game_count": 4,
    "games": [
      {
        "appid": 730,
        "name": "Counter-Strike 2",
        "playtime_2weeks": 132,
        "playtime_forever": 912,
        "img_icon_url": "8dbc71957312bbd3baea65848b545be9eae2a355",
        "has_community_visible_stats": true,
        "content_descriptorids": [
          2,
          5
        ]
      },
      {
        "appid": 739630,
        "name": "Phasmophobia",
        "playtime_forever": 55,
        "img_icon_url": "125673b382059f666ec81477173380a76e1df0be",
        "has_community_visible_stats": true
      },
      {
        "appid": 945360,
        "name": "Among Us",
        "playtime_forever": 174,
        "img_icon_url": "b82c3f46da8f3c918e1c9e0d18bd6fa8fcef6801",
        "has_community_visible_stats": true
      },
      {
        "appid": 2707930,
        "name": "Palia",
        "playtime_forever": 5933,
        "img_icon_url": "98de4ad85ffe8ab6d7b73f5aeb5b8295304fa6eb",
        "has_community_visible_stats": true
      }
    ]
  }
}